odoo/addons/delivery_seur_atlas/README.rst
odoo/addons/delivery_seur_atlas/__init__.py
odoo/addons/delivery_seur_atlas/__manifest__.py
odoo/addons/delivery_seur_atlas/i18n/delivery_seur_atlas.pot
odoo/addons/delivery_seur_atlas/i18n/es.po
odoo/addons/delivery_seur_atlas/models/__init__.py
odoo/addons/delivery_seur_atlas/models/delivery_carrier.py
odoo/addons/delivery_seur_atlas/models/seur_master_data.py
odoo/addons/delivery_seur_atlas/models/seur_request_atlas.py
odoo/addons/delivery_seur_atlas/readme/CONFIGURE.md
odoo/addons/delivery_seur_atlas/readme/CONTEXT.md
odoo/addons/delivery_seur_atlas/readme/CONTRIBUTORS.md
odoo/addons/delivery_seur_atlas/readme/DESCRIPTION.md
odoo/addons/delivery_seur_atlas/readme/INSTALL.md
odoo/addons/delivery_seur_atlas/readme/ROADMAP.md
odoo/addons/delivery_seur_atlas/readme/USAGE.md
odoo/addons/delivery_seur_atlas/static/description/icon.png
odoo/addons/delivery_seur_atlas/static/description/index.html
odoo/addons/delivery_seur_atlas/tests/__init__.py
odoo/addons/delivery_seur_atlas/tests/test_delivery_seur_atlas.py
odoo/addons/delivery_seur_atlas/views/delivery_carrier_views.xml
odoo_addon_delivery_seur_atlas-18.0.1.0.0.2.dist-info/METADATA
odoo_addon_delivery_seur_atlas-18.0.1.0.0.2.dist-info/WHEEL
odoo_addon_delivery_seur_atlas-18.0.1.0.0.2.dist-info/top_level.txt
odoo_addon_delivery_seur_atlas-18.0.1.0.0.2.dist-info/RECORD
